{
  "project_info": {
    "project_number": "547755357962",
    "firebase_url": "https://musictest-c4f7c-default-rtdb.firebaseio.com",
    "project_id": "musictest-c4f7c",
    "storage_bucket": "musictest-c4f7c.firebasestorage.app"
  },
  "client": [
    {
      "client_info": {
        "mobilesdk_app_id": "1:547755357962:android:78cc58e4327b086a006cf3",
        "android_client_info": {
          "package_name": "com.ali.musictest"
        }
      },
      "oauth_client": [],
      "api_key": [
        {
          "current_key": "AIzaSyCvrrC5-JPifnSLZck2vrpAe6teenHMOY8"
        }
      ],
      "services": {
        "appinvite_service": {
          "other_platform_oauth_client": []
        }
      }
    }
  ],
  "configuration_version": "1"
}